Trapezoidal_Fuzzy_Number/__init__.py
Trapezoidal_Fuzzy_Number-1.2.dist-info/LICENSE
Trapezoidal_Fuzzy_Number-1.2.dist-info/METADATA
Trapezoidal_Fuzzy_Number-1.2.dist-info/WHEEL
Trapezoidal_Fuzzy_Number-1.2.dist-info/top_level.txt
Trapezoidal_Fuzzy_Number-1.2.dist-info/RECORD
