Metadata-Version: 2.1
Name: Trapezoidal_Fuzzy_Number
Version: 1.2
Summary: A library to work with trapezoidal fuzzy numbers
Home-page: https://github.com/shayanfirouzian/Trapezoidal_Fuzzy_Number
Author: Shayan Firouzian
License: MIT
License-File: LICENSE
